README.rst
s3sign.py
setup.py
s3sign.egg-info/PKG-INFO
s3sign.egg-info/SOURCES.txt
s3sign.egg-info/dependency_links.txt
s3sign.egg-info/top_level.txt