Metadata-Version: 1.1
Name: s3sign
Version: 0.1.1
Summary: A library to generate AWS S3 Signed Requests
Home-page: https://github.com/alej0varas/s3sign
Author: Alexandre Varas
Author-email: alej0varas@gmail.com
License: GNU Library or Lesser General Public License (LGPL)
Platform: UNKNOWN
Classifier: Development Status :: 3 - Alpha
Classifier: Intended Audience :: Developers
Classifier: License :: OSI Approved :: GNU Library or Lesser General Public License (LGPL)
Classifier: Operating System :: OS Independent
Classifier: Topic :: Internet :: WWW/HTTP
Classifier: Topic :: Software Development :: Libraries
Classifier: Programming Language :: Python
Classifier: Programming Language :: Python :: 3
